eye_game/__init__.py
eye_game/api.py
eye_game/functions.py
eye_game-0.0.4.dist-info/METADATA
eye_game-0.0.4.dist-info/RECORD
eye_game-0.0.4.dist-info/WHEEL
eye_game-0.0.4.dist-info/top_level.txt
