Metadata-Version: 2.1
Name: eye-game
Version: 0.0.4
Summary: input: an image containing a human face; output: the eyeball direction
Home-page: https://github.com/VanjayDo/eye_game
Author: Vanjay Do
Author-email: vanjaydo@gmail.com
License: MIT Licence
Keywords: eye,eyeball,eye tracking,eyeball direction
Platform: any
Requires-Dist: face-recognition
Requires-Dist: numpy
Requires-Dist: opencv-python
Requires-Dist: pillow
